MANIFEST.in
README.md
setup.cfg
setup.py
version.txt
src/vdk/api/control/plugin/markers.py
src/vdk/api/control/plugin/specs.py
src/vdk/internal/control/main.py
src/vdk/internal/control/vdk_control_build_info.py
src/vdk/internal/control/command_groups/common_group/default.py
src/vdk/internal/control/command_groups/info_group/info.py
src/vdk/internal/control/command_groups/job/create.py
src/vdk/internal/control/command_groups/job/delete.py
src/vdk/internal/control/command_groups/job/deploy_cli.py
src/vdk/internal/control/command_groups/job/deploy_cli_impl.py
src/vdk/internal/control/command_groups/job/download_job.py
src/vdk/internal/control/command_groups/job/download_key.py
src/vdk/internal/control/command_groups/job/execute.py
src/vdk/internal/control/command_groups/job/list.py
src/vdk/internal/control/command_groups/job/properties.py
src/vdk/internal/control/command_groups/job/show.py
src/vdk/internal/control/command_groups/login_group/login.py
src/vdk/internal/control/command_groups/logout_group/logout.py
src/vdk/internal/control/command_groups/version_group/version.py
src/vdk/internal/control/configuration/default_options.py
src/vdk/internal/control/configuration/defaults_config.py
src/vdk/internal/control/configuration/log_config.py
src/vdk/internal/control/configuration/vdk_config.py
src/vdk/internal/control/exception/vdk_exception.py
src/vdk/internal/control/job/job_archive.py
src/vdk/internal/control/job/job_config.py
src/vdk/internal/control/job/sample_job/10_sql_step.sql
src/vdk/internal/control/job/sample_job/20_python_step.py
src/vdk/internal/control/job/sample_job/README.md
src/vdk/internal/control/job/sample_job/config.ini
src/vdk/internal/control/job/sample_job/requirements.txt
src/vdk/internal/control/plugin/control_plugin_manager.py
src/vdk/internal/control/rest_lib/factory.py
src/vdk/internal/control/rest_lib/rest_client_errors.py
src/vdk/internal/control/utils/cli_utils.py
src/vdk/internal/control/utils/control_utils.py
src/vdk_control_cli.egg-info/PKG-INFO
src/vdk_control_cli.egg-info/SOURCES.txt
src/vdk_control_cli.egg-info/dependency_links.txt
src/vdk_control_cli.egg-info/entry_points.txt
src/vdk_control_cli.egg-info/not-zip-safe
src/vdk_control_cli.egg-info/requires.txt
src/vdk_control_cli.egg-info/top_level.txt