Metadata-Version: 2.1
Name: vdk-control-cli
Version: 1.3.895138863
Summary: VDK Control CLI allows user to create, delete, manage and their Data Jobs in Kubernetes runtime.
Home-page: https://github.com/vmware/versatile-data-kit
Author: VMware Inc.
Author-email: aivanov@vmware.com
Project-URL: Documentation, https://github.com/vmware/versatile-data-kit/wiki
Project-URL: Source, https://github.com/vmware/versatile-data-kit/projects/vdk-control-cli
Platform: any
Classifier: Development Status :: 4 - Beta
Classifier: License :: OSI Approved :: Apache Software License
Classifier: Programming Language :: Python
Classifier: Programming Language :: Python :: 3.7
Classifier: Programming Language :: Python :: 3.8
Classifier: Programming Language :: Python :: 3.9
Classifier: Programming Language :: Python :: 3.10
Classifier: Programming Language :: Python :: 3.11
Requires-Python: <4,>=3.7
